.gitmodules
LICENSE
README.md
pyproject.toml
setup.cfg
setup.py
eigency/__init__.py
eigency/conversions.cpp
eigency/conversions.pxd
eigency/conversions.pyx
eigency/conversions_api.h
eigency/core.cpp
eigency/core.pxd
eigency/core.pyx
eigency/eigency.h
eigency/eigency_cpp.h
eigency.egg-info/PKG-INFO
eigency.egg-info/SOURCES.txt
eigency.egg-info/dependency_links.txt
eigency.egg-info/requires.txt
eigency.egg-info/top_level.txt
eigency/eigen/COPYING.APACHE
eigency/eigen/COPYING.BSD
eigency/eigen/COPYING.GPL
eigency/eigen/COPYING.LGPL
eigency/eigen/COPYING.MINPACK
eigency/eigen/COPYING.MPL2
eigency/eigen/COPYING.README
eigency/eigen/Eigen/Cholesky
eigency/eigen/Eigen/CholmodSupport
eigency/eigen/Eigen/Core
eigency/eigen/Eigen/Dense
eigency/eigen/Eigen/Eigen
eigency/eigen/Eigen/Eigenvalues
eigency/eigen/Eigen/Geometry
eigency/eigen/Eigen/Householder
eigency/eigen/Eigen/IterativeLinearSolvers
eigency/eigen/Eigen/Jacobi
eigency/eigen/Eigen/KLUSupport
eigency/eigen/Eigen/LU
eigency/eigen/Eigen/MetisSupport
eigency/eigen/Eigen/OrderingMethods
eigency/eigen/Eigen/PaStiXSupport
eigency/eigen/Eigen/PardisoSupport
eigency/eigen/Eigen/QR
eigency/eigen/Eigen/QtAlignedMalloc
eigency/eigen/Eigen/SPQRSupport
eigency/eigen/Eigen/SVD
eigency/eigen/Eigen/Sparse
eigency/eigen/Eigen/SparseCholesky
eigency/eigen/Eigen/SparseCore
eigency/eigen/Eigen/SparseLU
eigency/eigen/Eigen/SparseQR
eigency/eigen/Eigen/StdDeque
eigency/eigen/Eigen/StdList
eigency/eigen/Eigen/StdVector
eigency/eigen/Eigen/SuperLUSupport
eigency/eigen/Eigen/UmfPackSupport
eigency/eigen/Eigen/src/Cholesky/LDLT.h
eigency/eigen/Eigen/src/Cholesky/LLT.h
eigency/eigen/Eigen/src/Cholesky/LLT_LAPACKE.h
eigency/eigen/Eigen/src/CholmodSupport/CholmodSupport.h
eigency/eigen/Eigen/src/Core/ArithmeticSequence.h
eigency/eigen/Eigen/src/Core/Array.h
eigency/eigen/Eigen/src/Core/ArrayBase.h
eigency/eigen/Eigen/src/Core/ArrayWrapper.h
eigency/eigen/Eigen/src/Core/Assign.h
eigency/eigen/Eigen/src/Core/AssignEvaluator.h
eigency/eigen/Eigen/src/Core/Assign_MKL.h
eigency/eigen/Eigen/src/Core/BandMatrix.h
eigency/eigen/Eigen/src/Core/Block.h
eigency/eigen/Eigen/src/Core/BooleanRedux.h
