Metadata-Version: 2.4
Name: eigency
Version: 3.4.0.4
Summary: Cython interface between the numpy arrays and the Matrix/Array classes of the Eigen C++ library
Author-email: Wouter Boomsma <wb@di.ku.dk>, Felipe Bordeu <felipebordeu@gmail.com>
Maintainer-email: Felipe Bordeu <felipebordeu@gmail.com>, Wouter Boomsma <wb@di.ku.dk>
Project-URL: Homepage, https://github.com/eigency-org/eigency
Classifier: Intended Audience :: Developers
Classifier: Programming Language :: C++
Classifier: Programming Language :: Cython
Classifier: Programming Language :: Python :: 3.9
Classifier: Programming Language :: Python :: 3.10
Classifier: Programming Language :: Python :: 3.11
Classifier: Programming Language :: Python :: 3.12
Classifier: Programming Language :: Python :: 3.13
Requires-Python: >=3.9
License-File: LICENSE
Requires-Dist: numpy>=1.23.5
Dynamic: license-file
